License.txt
MANIFEST.in
README.rst
requirements.txt
setup.py
pyrcmd3/VERSION
pyrcmd3/__init__.py
pyrcmd3/exceptions.py
pyrcmd3/ssh.py
pyrcmd3.egg-info/PKG-INFO
pyrcmd3.egg-info/SOURCES.txt
pyrcmd3.egg-info/dependency_links.txt
pyrcmd3.egg-info/requires.txt
pyrcmd3.egg-info/top_level.txt