Metadata-Version: 1.1
Name: pyrcmd3
Version: 0.1.0
Summary: Python3 Remote Commands toolkit
Home-page: https://github.com/marreta/pyrcmd3/
Author: Bruno Costa, Kairo Araujo
Author-email: coder@marreta.org
License: BSD
Keywords: Python3 Remote Command Commands SSH Toolkit
Platform: Posix; MacOS X; Windows
Classifier: Development Status :: 4 - Beta
Classifier: Intended Audience :: Developers
Classifier: License :: OSI Approved :: BSD License
Classifier: Operating System :: Unix
Classifier: Topic :: System :: Shells
Classifier: Programming Language :: Python
Classifier: Programming Language :: Python :: 3
Classifier: Programming Language :: Python :: 3.2
Classifier: Programming Language :: Python :: 3.3
Classifier: Programming Language :: Python :: 3.4
Classifier: Programming Language :: Python :: 3.5
